python_bladerf/__init__.py
python_bladerf/__main__.py
python_bladerf/pybladerf_tools/__init__.py
python_bladerf/pybladerf_tools/pybladerf_info.py
python_bladerf/pybladerf_tools/pybladerf_sweep.cpython-312-darwin.so
python_bladerf/pybladerf_tools/pybladerf_transfer.cpython-312-darwin.so
python_bladerf/pybladerf_tools/utils.py
python_bladerf/pylibbladerf/__android.py
python_bladerf/pylibbladerf/__init__.py
python_bladerf/pylibbladerf/pybladerf.cpython-312-darwin.so
python_bladerf/pylibbladerf/pybladerf.pyi
python_bladerf-1.3.0.dist-info/licenses/LICENSE
python_bladerf-1.3.0.dist-info/METADATA
python_bladerf-1.3.0.dist-info/WHEEL
python_bladerf-1.3.0.dist-info/entry_points.txt
python_bladerf-1.3.0.dist-info/top_level.txt
python_bladerf-1.3.0.dist-info/RECORD
