Metadata-Version: 2.4
Name: python_bladerf
Version: 1.3.0
Summary: This is a wrapper for bladerf.
Author-email: Leonid Gvozdev <leo.gvozdev.dev@gmail.com>
Project-URL: Homepage, https://github.com/GvozdevLeonid/python_bladerf
Project-URL: Bug Tracker, https://github.com/GvozdevLeonid/python_bladerf/issues
Classifier: License :: OSI Approved :: MIT License
Classifier: Programming Language :: Python :: 3
Classifier: Operating System :: Android
Classifier: Operating System :: POSIX :: Linux
Classifier: Operating System :: MacOS
Classifier: Operating System :: MacOS :: MacOS X
Classifier: Operating System :: Microsoft :: Windows
Requires-Python: >=3.9
License-File: LICENSE
Requires-Dist: numpy
Dynamic: license-file
